MANIFEST.in
README.md
setup.cfg
setup.py
docassemble/__init__.py
docassemble.income.egg-info/PKG-INFO
docassemble.income.egg-info/SOURCES.txt
docassemble.income.egg-info/dependency_links.txt
docassemble.income.egg-info/namespace_packages.txt
docassemble.income.egg-info/not-zip-safe
docassemble.income.egg-info/top_level.txt
docassemble/income/__init__.py
docassemble/income/income.py
docassemble/income/data/questions/demo_basic_income_questions.yml
docassemble/income/data/questions/financial_statement.yml
docassemble/income/data/questions/income_test.yml
docassemble/income/data/questions/ledger_test.yml
docassemble/income/data/questions/simple_income_questions.yml
docassemble/income/data/sources/README.md
docassemble/income/data/static/README.md
docassemble/income/data/templates/README.md