Metadata-Version: 2.1
Name: docassemble.income
Version: 0.0.36
Summary: A module to help with gathering a financial statement, including hourly wages
Home-page: https://docassemble.org
Author: Quinten Steenhuis
Author-email: admin@admin.com
License: The MIT License (MIT)
Platform: UNKNOWN
